intrascraper/__init__.py
intrascraper/intrascraper.py
intra42-0.1.5.dist-info/METADATA
intra42-0.1.5.dist-info/WHEEL
intra42-0.1.5.dist-info/top_level.txt
intra42-0.1.5.dist-info/RECORD
