Metadata-Version: 2.1
Name: intra42
Version: 0.1.5
Summary: Intra 42 utility package
Home-page: https://github.com/Xentiie/py_intra42
Author: Rémi Claire
Author-email: reclaire@student.42mulhouse.fr
License: BSD 2-clause
Requires-Dist: requests
Requires-Dist: bs4
